horloadist/__init__.py
horloadist/linsolve.py
horloadist/nlsolve.py
horloadist/node.py
horloadist/polygon.py
horloadist/stiffnesses.py
horloadist/structure.py
horloadist/utils.py
horloadist-1.2.0.dist-info/LICENSE.txt
horloadist-1.2.0.dist-info/METADATA
horloadist-1.2.0.dist-info/WHEEL
horloadist-1.2.0.dist-info/top_level.txt
horloadist-1.2.0.dist-info/RECORD
