Metadata-Version: 2.1
Name: horloadist
Version: 1.2.0
Summary: Calculates the horizontal load distribution on supports in the plane
Author-email: "L.Maul" <saculluam@hotmail.com>
Maintainer-email: "L.Maul" <saculluam@hotmail.com>
License: MIT License
Project-URL: Bug Reports, https://github.com/LuMaul/horloadist.git
Project-URL: Source, https://github.com/LuMaul/horloadist.git
Keywords: load distribution, horloadist, development, civil engineering
Classifier: Development Status :: 3 - Alpha
Classifier: Intended Audience :: Developers
Classifier: Topic :: Software Development :: Build Tools
Classifier: License :: OSI Approved :: MIT License
Classifier: Programming Language :: Python :: 3
Classifier: Programming Language :: Python :: 3.8
Classifier: Programming Language :: Python :: 3.9
Classifier: Programming Language :: Python :: 3.10
Classifier: Programming Language :: Python :: 3.11
Classifier: Programming Language :: Python :: 3.12
Classifier: Programming Language :: Python :: 3 :: Only
Requires-Python: >=3.8
License-File: LICENSE.txt
Requires-Dist: numpy
Requires-Dist: pandas
Requires-Dist: scipy
Requires-Dist: matplotlib
